Metadata-Version: 2.4
Name: llm-templates-github
Version: 0.1
Summary: Laod LLM templates from GitHub repositories
Author: Simon Willison
License: Apache-2.0
Project-URL: Homepage, https://github.com/simonw/llm-templates-github
Project-URL: Changelog, https://github.com/simonw/llm-templates-github/releases
Project-URL: Issues, https://github.com/simonw/llm-templates-github/issues
Project-URL: CI, https://github.com/simonw/llm-templates-github/actions
Classifier: License :: OSI Approved :: Apache Software License
Requires-Python: >=3.9
License-File: LICENSE
Requires-Dist: llm>=0.24
Provides-Extra: test
Requires-Dist: pytest; extra == "test"
Requires-Dist: pytest-httpx; extra == "test"
Dynamic: license-file
